{"Sutter Health Park": {"run": 1.21, "hr": 1.31, "doubles": 1.15, "singles": 1.03, "run_stadium": 1.2, "hr_stadium": 1.32, "run_weather": 1.01, "hr_weather": 0.99, "source": "ballparkpal"}, "Rate Field": {"run": 1.13, "hr": 1.16, "doubles": 1.03, "singles": 1.06, "run_stadium": 1.0, "hr_stadium": 1.02, "run_weather": 1.13, "hr_weather": 1.13, "source": "ballparkpal"}, "Great American BP": {"run": 1.06, "hr": 1.12, "doubles": 1.04, "singles": 0.95, "run_stadium": 1.11, "hr_stadium": 1.17, "run_weather": 0.96, "hr_weather": 0.95, "source": "ballparkpal"}, "Target Field": {"run": 1.04, "hr": 1.01, "doubles": 1.02, "singles": 1.02, "run_stadium": 1.01, "hr_stadium": 0.94, "run_weather": 1.03, "hr_weather": 1.07, "source": "ballparkpal"}, "Fenway Park": {"run": 1.0, "hr": 0.75, "doubles": 1.18, "singles": 1.06, "run_stadium": 1.1, "hr_stadium": 0.9299999999999999, "run_weather": 0.9, "hr_weather": 0.8200000000000001, "source": "ballparkpal"}, "Progressive Field": {"run": 0.99, "hr": 0.9299999999999999, "doubles": 1.04, "singles": 0.97, "run_stadium": 0.99, "hr_stadium": 0.97, "run_weather": 1.0, "hr_weather": 0.96, "source": "ballparkpal"}, "Daikin Park": {"run": 0.96, "hr": 1.05, "doubles": 0.89, "singles": 0.96, "run_stadium": 0.95, "hr_stadium": 1.06, "run_weather": 1.0, "hr_weather": 1.0, "source": "ballparkpal"}, "American Family Fld": {"run": 0.95, "hr": 1.06, "doubles": 0.87, "singles": 0.92, "run_stadium": 0.97, "hr_stadium": 1.1, "run_weather": 0.98, "hr_weather": 0.96, "source": "ballparkpal"}, "Oriole Park": {"run": 0.95, "hr": 0.83, "doubles": 0.9, "singles": 1.1, "run_stadium": 1.06, "hr_stadium": 0.99, "run_weather": 0.9, "hr_weather": 0.84, "source": "ballparkpal"}, "PNC Park": {"run": 0.95, "hr": 0.78, "doubles": 1.04, "singles": 1.02, "run_stadium": 1.0, "hr_stadium": 0.86, "run_weather": 0.95, "hr_weather": 0.92, "source": "ballparkpal"}, "Dodger Stadium": {"run": 0.94, "hr": 1.08, "doubles": 0.94, "singles": 0.9299999999999999, "run_stadium": 1.0, "hr_stadium": 1.18, "run_weather": 0.94, "hr_weather": 0.9, "source": "ballparkpal"}, "Rogers Centre": {"run": 0.94, "hr": 1.0, "doubles": 0.96, "singles": 0.97, "run_stadium": 0.98, "hr_stadium": 1.05, "run_weather": 0.96, "hr_weather": 0.95, "source": "ballparkpal"}, "Globe Life Field": {"run": 0.9299999999999999, "hr": 0.9, "doubles": 0.9299999999999999, "singles": 0.98, "run_stadium": 0.9299999999999999, "hr_stadium": 0.91, "run_weather": 1.0, "hr_weather": 0.99, "source": "ballparkpal"}, "Truist Park": {"run": 0.87, "hr": 0.78, "doubles": 0.9299999999999999, "singles": 0.99, "run_stadium": 0.96, "hr_stadium": 0.96, "run_weather": 0.91, "hr_weather": 0.8200000000000001, "source": "ballparkpal"}, "Citi Field": {"run": 0.85, "hr": 0.88, "doubles": 0.71, "singles": 0.98, "run_stadium": 0.92, "hr_stadium": 0.99, "run_weather": 0.9299999999999999, "hr_weather": 0.89, "source": "ballparkpal"}}