{"Great American BP": {"run": 1.15, "hr": 1.29, "doubles": 1.03, "singles": 0.97, "run_stadium": 1.09, "hr_stadium": 1.1400000000000001, "run_weather": 1.06, "hr_weather": 1.15, "source": "ballparkpal"}, "Oriole Park": {"run": 1.09, "hr": 1.06, "doubles": 1.08, "singles": 1.07, "run_stadium": 1.06, "hr_stadium": 1.0, "run_weather": 1.04, "hr_weather": 1.06, "source": "ballparkpal"}, "Nationals Park": {"run": 1.06, "hr": 1.09, "doubles": 1.04, "singles": 1.03, "run_stadium": 1.04, "hr_stadium": 1.03, "run_weather": 1.03, "hr_weather": 1.06, "source": "ballparkpal"}, "Rate Field": {"run": 1.05, "hr": 1.1, "doubles": 0.91, "singles": 1.06, "run_stadium": 1.01, "hr_stadium": 1.03, "run_weather": 1.05, "hr_weather": 1.07, "source": "ballparkpal"}, "PNC Park": {"run": 1.05, "hr": 1.02, "doubles": 1.16, "singles": 0.95, "run_stadium": 0.99, "hr_stadium": 0.85, "run_weather": 1.06, "hr_weather": 1.17, "source": "ballparkpal"}, "Comerica Park": {"run": 1.01, "hr": 0.96, "doubles": 1.07, "singles": 1.02, "run_stadium": 0.98, "hr_stadium": 0.88, "run_weather": 1.04, "hr_weather": 1.07, "source": "ballparkpal"}, "Target Field": {"run": 0.99, "hr": 0.95, "doubles": 1.02, "singles": 0.99, "run_stadium": 1.0, "hr_stadium": 0.9299999999999999, "run_weather": 0.99, "hr_weather": 1.02, "source": "ballparkpal"}, "Oracle Park": {"run": 0.96, "hr": 0.79, "doubles": 1.03, "singles": 1.08, "run_stadium": 1.0, "hr_stadium": 0.84, "run_weather": 0.97, "hr_weather": 0.95, "source": "ballparkpal"}, "Dodger Stadium": {"run": 0.95, "hr": 1.18, "doubles": 0.94, "singles": 0.88, "run_stadium": 1.0, "hr_stadium": 1.17, "run_weather": 0.95, "hr_weather": 1.02, "source": "ballparkpal"}, "LoanDepot Park": {"run": 0.94, "hr": 0.87, "doubles": 1.01, "singles": 0.98, "run_stadium": 0.95, "hr_stadium": 0.87, "run_weather": 1.0, "hr_weather": 1.0, "source": "ballparkpal"}, "Tropicana Field": {"run": 0.94, "hr": 0.97, "doubles": 0.9299999999999999, "singles": 0.92, "run_stadium": 0.94, "hr_stadium": 0.96, "run_weather": 1.0, "hr_weather": 1.01, "source": "ballparkpal"}, "Citi Field": {"run": 0.9299999999999999, "hr": 1.08, "doubles": 0.75, "singles": 0.95, "run_stadium": 0.92, "hr_stadium": 0.99, "run_weather": 1.01, "hr_weather": 1.09, "source": "ballparkpal"}, "Globe Life Field": {"run": 0.9299999999999999, "hr": 0.89, "doubles": 0.94, "singles": 0.99, "run_stadium": 0.9299999999999999, "hr_stadium": 0.89, "run_weather": 1.0, "hr_weather": 0.99, "source": "ballparkpal"}, "Busch Stadium": {"run": 0.92, "hr": 0.9299999999999999, "doubles": 0.94, "singles": 1.0, "run_stadium": 0.94, "hr_stadium": 0.91, "run_weather": 0.98, "hr_weather": 1.02, "source": "ballparkpal"}, "Petco Park": {"run": 0.87, "hr": 0.94, "doubles": 0.78, "singles": 0.94, "run_stadium": 0.9299999999999999, "hr_stadium": 0.97, "run_weather": 0.94, "hr_weather": 0.97, "source": "ballparkpal"}}