{
  "date": "2026-04-08",
  "generated_at": "2026-04-08T02:47:52.838674Z",
  "total_games": 15,
  "season_blend": {
    "current": 0.0,
    "prior": 1.0,
    "games_est": 9,
    "label": "prior_season_only"
  },
  "games": [
    {
      "game_pk": 823403,
      "game_date": "2026-04-08",
      "game_time": "2026-04-08T16:35:00Z",
      "status": "Preview",
      "venue": "PNC Park",
      "park_factors": {
        "hr": 100,
        "run": 100
      },
      "weather": {
        "condition": "",
        "temp_f": "",
        "wind": ""
      },
      "away": {
        "team_name": "San Diego Padres",
        "team_abbr": "SD"
      },
      "home": {
        "team_name": "Pittsburgh Pirates",
        "team_abbr": "PIT"
      },
      "pitchers": {
        "away": {
          "id": 650633,
          "name": "Michael King",
          "hand": "R",
          "stats": {
            "id": 650633,
            "name": "Michael King",
            "season": {
              "era": 3.4,
              "whip": 1.2,
              "ip": 73.3,
              "gs": 15,
              "k_pct": 24.7,
              "bb_pct": 8.4,
              "xera": null,
              "xfip": null,
              "swstr": null,
              "fip": null,
              "k_bb": null,
              "_source": "2025_only",
              "_blend": "prior_season_only"
            },
            "recent_form": {
              "total_pitches": 334,
              "ip_est": 4.4,
              "k_pct": 21.1,
              "bb_pct": 8.9,
              "swstr_pct": 12.0,
              "csw_pct": 27.8,
              "hard_hit_pct": 27.8,
              "barrel_pct": 2.8,
              "xba_allowed": 0.323,
              "xslg_allowed": 0.612,
              "xwoba_allowed": 0.338,
              "pitch_mix": {
                "SI": 35.6,
                "CH": 24.0,
                "ST": 21.3,
                "FF": 16.5,
                "SL": 2.7
              }
            }
          },
          "projection": {
            "ip_proj": 4.7,
            "outs_proj": 14.1,
            "k_proj": 3.7,
            "bb_proj": 1.3,
            "hits_proj": 4.3,
            "era_proj": 3.4,
            "runs_proj": 1.8,
            "er_proj": 1.8,
            "k_pct_adj": 23.3,
            "csw_pct": 27.8,
            "xfip": 3.4,
            "quality_start_prob": 66.0
          },
          "prop_lines": {
            "pitcher_strikeouts_over": {
              "fanduel": {
                "line": 5.5,
                "price": -128
              },
              "bovada": {
                "line": 5.5,
                "price": -125
              }
            },
            "pitcher_strikeouts_under": {
              "fanduel": {
                "line": 5.5,
                "price": -104
              },
              "bovada": {
                "line": 5.5,
                "price": -105
              }
            }
          },
          "edges": {
            "K_under": {
              "proj": 3.7,
              "line": 5.5,
              "diff": -1.8,
              "edge_pct": -32.7,
              "lean": "UNDER",
              "flag": true,
              "best_book": "fanduel"
            }
          }
        },
        "home": {
          "id": 656605,
          "name": "Mitch Keller",
          "hand": "R",
          "stats": {
            "id": 656605,
            "name": "Mitch Keller",
            "season": {
              "era": 4.2,
              "whip": 1.3,
              "ip": 176.3,
              "gs": 32,
              "k_pct": 20.0,
              "bb_pct": 6.8,
              "xera": null,
              "xfip": null,
              "swstr": null,
              "fip": null,
              "k_bb": null,
              "_source": "2025_only",
              "_blend": "prior_season_only"
            },
            "recent_form": {
              "total_pitches": 322,
              "ip_est": 4.8,
              "k_pct": 22.2,
              "bb_pct": 9.9,
              "swstr_pct": 7.8,
              "csw_pct": 23.0,
              "hard_hit_pct": 22.0,
              "barrel_pct": 0.9,
              "xba_allowed": 0.297,
              "xslg_allowed": 0.388,
              "xwoba_allowed": 0.287,
              "pitch_mix": {
                "FF": 32.3,
                "SI": 25.5,
                "ST": 20.8,
                "CH": 13.0,
                "CU": 6.8,
                "SL": 1.6
              }
            }
          },
          "projection": {
            "ip_proj": 5.2,
            "outs_proj": 15.6,
            "k_proj": 3.6,
            "bb_proj": 1.2,
            "hits_proj": 4.3,
            "era_proj": 4.2,
            "runs_proj": 2.4,
            "er_proj": 2.4,
            "k_pct_adj": 20.9,
            "csw_pct": 23.0,
            "xfip": 4.2,
            "quality_start_prob": 63.0
          },
          "prop_lines": {
            "pitcher_strikeouts_over": {
              "fanduel": {
                "line": 4.5,
                "price": 106
              },
              "bovada": {
                "line": 4.5,
                "price": 105
              }
            },
            "pitcher_strikeouts_under": {
              "fanduel": {
                "line": 4.5,
                "price": -140
              },
              "bovada": {
                "line": 4.5,
                "price": -135
              }
            }
          },
          "edges": {
            "K_under": {
              "proj": 3.6,
              "line": 4.5,
              "diff": -0.9,
              "edge_pct": -20.0,
              "lean": "UNDER",
              "flag": true,
              "best_book": "fanduel"
            }
          }
        }
      },
      "projected_boxscore": {
        "away": [],
        "home": []
      },
      "top_edges": [
        {
          "player": "Michael King",
          "type": "K_under",
          "proj": 3.7,
          "line": 5.5,
          "diff": -1.8,
          "edge_pct": -32.7,
          "lean": "UNDER",
          "flag": true,
          "best_book": "fanduel"
        },
        {
          "player": "Mitch Keller",
          "type": "K_under",
          "proj": 3.6,
          "line": 4.5,
          "diff": -0.9,
          "edge_pct": -20.0,
          "lean": "UNDER",
          "flag": true,
          "best_book": "fanduel"
        }
      ],
      "game_score": {},
      "game_line_edges": {}
    },
    {
      "game_pk": 824455,
      "game_date": "2026-04-08",
      "game_time": "2026-04-08T17:10:00Z",
      "status": "Preview",
      "venue": "Progressive Field",
      "park_factors": {
        "hr": 100,
        "run": 100
      },
      "weather": {
        "condition": "",
        "temp_f": "",
        "wind": ""
      },
      "away": {
        "team_name": "Kansas City Royals",
        "team_abbr": "KC"
      },
      "home": {
        "team_name": "Cleveland Guardians",
        "team_abbr": "CLE"
      },
      "pitchers": {
        "away": {
          "id": 666142,
          "name": "Cole Ragans",
          "hand": "L",
          "stats": {
            "id": 666142,
            "name": "Cole Ragans",
            "season": {
              "era": 4.7,
              "whip": 1.2,
              "ip": 61.7,
              "gs": 13,
              "k_pct": 38.1,
              "bb_pct": 7.8,
              "xera": null,
              "xfip": null,
              "swstr": null,
              "fip": null,
              "k_bb": null,
              "_source": "2025_only",
              "_blend": "prior_season_only"
            },
            "recent_form": {
              "total_pitches": 379,
              "ip_est": 4.0,
              "k_pct": 32.6,
              "bb_pct": 9.5,
              "swstr_pct": 16.6,
              "csw_pct": 29.3,
              "hard_hit_pct": 24.3,
              "barrel_pct": 0.0,
              "xba_allowed": 0.35,
              "xslg_allowed": 0.632,
              "xwoba_allowed": 0.319,
              "pitch_mix": {
                "FF": 52.8,
                "SL": 18.2,
                "CH": 17.4,
                "KC": 8.7,
                "FC": 2.9
              }
            }
          },
          "projection": {
            "ip_proj": 4.4,
            "outs_proj": 13.2,
            "k_proj": 5.6,
            "bb_proj": 1.1,
            "hits_proj": 4.3,
            "era_proj": 4.7,
            "runs_proj": 2.3,
            "er_proj": 2.3,
            "k_pct_adj": 35.9,
            "csw_pct": 29.3,
            "xfip": 4.7,
            "quality_start_prob": 54.0
          },
          "prop_lines": {},
          "edges": {}
        },
        "home": {
          "id": 676282,
          "name": "Joey Cantillo",
          "hand": "L",
          "stats": {
            "id": 676282,
            "name": "Joey Cantillo",
            "season": {
              "era": 3.2,
              "whip": 1.3,
              "ip": 95.3,
              "gs": 13,
              "k_pct": 26.9,
              "bb_pct": 10.5,
              "xera": null,
              "xfip": null,
              "swstr": null,
              "fip": null,
              "k_bb": null,
              "_source": "2025_only",
              "_blend": "prior_season_only"
            },
            "recent_form": {
              "total_pitches": 299,
              "ip_est": 4.2,
              "k_pct": 33.3,
              "bb_pct": 8.7,
              "swstr_pct": 12.0,
              "csw_pct": 31.4,
              "hard_hit_pct": 17.2,
              "barrel_pct": 0.0,
              "xba_allowed": 0.301,
              "xslg_allowed": 0.433,
              "xwoba_allowed": 0.277,
              "pitch_mix": {
                "FF": 43.5,
                "CH": 26.1,
                "CU": 15.7,
                "SL": 14.7
              }
            }
          },
          "projection": {
            "ip_proj": 6.1,
            "outs_proj": 18.3,
            "k_proj": 6.6,
            "bb_proj": 2.1,
            "hits_proj": 5.2,
            "era_proj": 3.2,
            "runs_proj": 2.2,
            "er_proj": 2.2,
            "k_pct_adj": 29.5,
            "csw_pct": 31.4,
            "xfip": 3.2,
            "quality_start_prob": 76.0
          },
          "prop_lines": {},
          "edges": {}
        }
      },
      "projected_boxscore": {
        "away": [],
        "home": []
      },
      "top_edges": [],
      "game_score": {},
      "game_line_edges": {}
    },
    {
      "game_pk": 824779,
      "game_date": "2026-04-08",
      "game_time": "2026-04-08T17:35:00Z",
      "status": "Preview",
      "venue": "Fenway Park",
      "park_factors": {
        "hr": 105,
        "run": 103
      },
      "weather": {
        "condition": "",
        "temp_f": "",
        "wind": ""
      },
      "away": {
        "team_name": "Milwaukee Brewers",
        "team_abbr": "MIL"
      },
      "home": {
        "team_name": "Boston Red Sox",
        "team_abbr": "BOS"
      },
      "pitchers": {
        "away": {
          "id": 675660,
          "name": "Shane Drohan",
          "hand": "L",
          "stats": {
            "id": 675660,
            "name": "Shane Drohan",
            "season": {},
            "recent_form": {
              "total_pitches": 144,
              "ip_est": 3.4,
              "k_pct": 24.2,
              "bb_pct": 9.1,
              "swstr_pct": 6.9,
              "csw_pct": 21.5,
              "hard_hit_pct": 18.2,
              "barrel_pct": 1.8,
              "xba_allowed": null,
              "xslg_allowed": null,
              "xwoba_allowed": null,
              "pitch_mix": {
                "FF": 38.2,
                "FC": 19.4,
                "SL": 18.8,
                "CH": 13.2,
                "CU": 7.6,
                "SI": 2.8
              }
            }
          },
          "projection": {
            "ip_proj": null,
            "outs_proj": null,
            "k_proj": null,
            "bb_proj": null,
            "hits_proj": null,
            "era_proj": null,
            "runs_proj": null,
            "er_proj": null,
            "k_pct_adj": 24.2,
            "csw_pct": 21.5,
            "xfip": null,
            "quality_start_prob": null
          },
          "prop_lines": {},
          "edges": {}
        },
        "home": {
          "id": 543243,
          "name": "Sonny Gray",
          "hand": "R",
          "stats": {
            "id": 543243,
            "name": "Sonny Gray",
            "season": {
              "era": 4.3,
              "whip": 1.2,
              "ip": 180.7,
              "gs": 32,
              "k_pct": 26.7,
              "bb_pct": 5.0,
              "xera": null,
              "xfip": null,
              "swstr": null,
              "fip": null,
              "k_bb": null,
              "_source": "2025_only",
              "_blend": "prior_season_only"
            },
            "recent_form": {
              "total_pitches": 374,
              "ip_est": 4.3,
              "k_pct": 24.7,
              "bb_pct": 6.2,
              "swstr_pct": 7.8,
              "csw_pct": 25.9,
              "hard_hit_pct": 24.6,
              "barrel_pct": 0.0,
              "xba_allowed": 0.327,
              "xslg_allowed": 0.618,
              "xwoba_allowed": 0.322,
              "pitch_mix": {
                "SI": 25.1,
                "FF": 18.7,
                "FC": 17.4,
                "ST": 17.1,
                "CU": 16.0,
                "CH": 4.5,
                "SL": 0.8,
                "CS": 0.3
              }
            }
          },
          "projection": {
            "ip_proj": 5.1,
            "outs_proj": 15.3,
            "k_proj": 4.4,
            "bb_proj": 0.8,
            "hits_proj": 4.7,
            "era_proj": 4.39,
            "runs_proj": 2.5,
            "er_proj": 2.5,
            "k_pct_adj": 25.9,
            "csw_pct": 25.9,
            "xfip": 4.3,
            "quality_start_prob": 60.0
          },
          "prop_lines": {},
          "edges": {}
        }
      },
      "projected_boxscore": {
        "away": [],
        "home": []
      },
      "top_edges": [],
      "game_score": {},
      "game_line_edges": {}
    },
    {
      "game_pk": 824617,
      "game_date": "2026-04-08",
      "game_time": "2026-04-08T18:10:00Z",
      "status": "Preview",
      "venue": "Rate Field",
      "park_factors": {
        "hr": 100,
        "run": 100
      },
      "weather": {
        "condition": "",
        "temp_f": "",
        "wind": ""
      },
      "away": {
        "team_name": "Baltimore Orioles",
        "team_abbr": "BAL"
      },
      "home": {
        "team_name": "Chicago White Sox",
        "team_abbr": "CWS"
      },
      "pitchers": {
        "away": {
          "id": 680694,
          "name": "Kyle Bradish",
          "hand": "R",
          "stats": {
            "id": 680694,
            "name": "Kyle Bradish",
            "season": {
              "era": 2.5,
              "whip": 1.0,
              "ip": 32.0,
              "gs": 6,
              "k_pct": 37.3,
              "bb_pct": 7.9,
              "xera": null,
              "xfip": null,
              "swstr": null,
              "fip": null,
              "k_bb": null,
              "_source": "2025_only",
              "_blend": "prior_season_only"
            },
            "recent_form": {
              "total_pitches": 311,
              "ip_est": 4.6,
              "k_pct": 19.2,
              "bb_pct": 12.8,
              "swstr_pct": 12.2,
              "csw_pct": 27.3,
              "hard_hit_pct": 30.2,
              "barrel_pct": 1.2,
              "xba_allowed": 0.242,
              "xslg_allowed": 0.429,
              "xwoba_allowed": 0.269,
              "pitch_mix": {
                "SL": 36.0,
                "SI": 33.1,
                "CU": 16.4,
                "FF": 14.5
              }
            }
          },
          "projection": {
            "ip_proj": 5.0,
            "outs_proj": 15.0,
            "k_proj": 5.0,
            "bb_proj": 1.3,
            "hits_proj": 3.4,
            "era_proj": 2.5,
            "runs_proj": 1.4,
            "er_proj": 1.4,
            "k_pct_adj": 30.1,
            "csw_pct": 27.3,
            "xfip": 2.5,
            "quality_start_prob": 75.0
          },
          "prop_lines": {
            "pitcher_strikeouts_over": {
              "draftkings": {
                "line": 5.5,
                "price": -144
              }
            },
            "pitcher_strikeouts_under": {
              "draftkings": {
                "line": 5.5,
                "price": 113
              }
            },
            "pitcher_outs_over": {
              "draftkings": {
                "line": 15.5,
                "price": 131
              },
              "bovada": {
                "line": 15.5,
                "price": 135
              }
            },
            "pitcher_outs_under": {
              "draftkings": {
                "line": 15.5,
                "price": -175
              },
              "bovada": {
                "line": 15.5,
                "price": -175
              }
            }
          },
          "edges": {}
        },
        "home": {
          "id": 680732,
          "name": "Sean Burke",
          "hand": "R",
          "stats": {
            "id": 680732,
            "name": "Sean Burke",
            "season": {
              "era": 4.2,
              "whip": 1.4,
              "ip": 134.3,
              "gs": 22,
              "k_pct": 22.3,
              "bb_pct": 10.6,
              "xera": null,
              "xfip": null,
              "swstr": null,
              "fip": null,
              "k_bb": null,
              "_source": "2025_only",
              "_blend": "prior_season_only"
            },
            "recent_form": {
              "total_pitches": 328,
              "ip_est": 4.9,
              "k_pct": 26.8,
              "bb_pct": 6.1,
              "swstr_pct": 9.5,
              "csw_pct": 25.6,
              "hard_hit_pct": 26.7,
              "barrel_pct": 0.8,
              "xba_allowed": 0.36,
              "xslg_allowed": 0.556,
              "xwoba_allowed": 0.289,
              "pitch_mix": {
                "FF": 43.0,
                "KC": 19.2,
                "SL": 18.3,
                "SI": 12.5,
                "CH": 7.0
              }
            }
          },
          "projection": {
            "ip_proj": 5.6,
            "outs_proj": 16.8,
            "k_proj": 4.5,
            "bb_proj": 2.0,
            "hits_proj": 5.7,
            "era_proj": 4.2,
            "runs_proj": 2.6,
            "er_proj": 2.6,
            "k_pct_adj": 24.1,
            "csw_pct": 25.6,
            "xfip": 4.2,
            "quality_start_prob": 65.0
          },
          "prop_lines": {
            "pitcher_strikeouts_over": {
              "draftkings": {
                "line": 5.5,
                "price": -115
              }
            },
            "pitcher_strikeouts_under": {
              "draftkings": {
                "line": 5.5,
                "price": -111
              }
            },
            "pitcher_outs_over": {
              "draftkings": {
                "line": 15.5,
                "price": 129
              },
              "bovada": {
                "line": 15.5,
                "price": 130
              }
            },
            "pitcher_outs_under": {
              "draftkings": {
                "line": 15.5,
                "price": -172
              },
              "bovada": {
                "line": 15.5,
                "price": -170
              }
            }
          },
          "edges": {
            "K_under": {
              "proj": 4.5,
              "line": 5.5,
              "diff": -1.0,
              "edge_pct": -18.2,
              "lean": "UNDER",
              "flag": true,
              "best_book": "draftkings"
            }
          }
        }
      },
      "projected_boxscore": {
        "away": [],
        "home": []
      },
      "top_edges": [
        {
          "player": "Sean Burke",
          "type": "K_under",
          "proj": 4.5,
          "line": 5.5,
          "diff": -1.0,
          "edge_pct": -18.2,
          "lean": "UNDER",
          "flag": true,
          "best_book": "draftkings"
        }
      ],
      "game_score": {},
      "game_line_edges": {}
    },
    {
      "game_pk": 822915,
      "game_date": "2026-04-08",
      "game_time": "2026-04-08T18:35:00Z",
      "status": "Preview",
      "venue": "Globe Life Field",
      "park_factors": {
        "hr": 107,
        "run": 102
      },
      "weather": {
        "condition": "",
        "temp_f": "",
        "wind": ""
      },
      "away": {
        "team_name": "Seattle Mariners",
        "team_abbr": "SEA"
      },
      "home": {
        "team_name": "Texas Rangers",
        "team_abbr": "TEX"
      },
      "pitchers": {
        "away": {
          "id": 693433,
          "name": "Bryan Woo",
          "hand": "R",
          "stats": {
            "id": 693433,
            "name": "Bryan Woo",
            "season": {
              "era": 2.9,
              "whip": 0.9,
              "ip": 186.7,
              "gs": 30,
              "k_pct": 27.1,
              "bb_pct": 4.9,
              "xera": null,
              "xfip": null,
              "swstr": null,
              "fip": null,
              "k_bb": null,
              "_source": "2025_only",
              "_blend": "prior_season_only"
            },
            "recent_form": {
              "total_pitches": 293,
              "ip_est": 5.6,
              "k_pct": 28.4,
              "bb_pct": 2.5,
              "swstr_pct": 13.3,
              "csw_pct": 29.4,
              "hard_hit_pct": 24.1,
              "barrel_pct": 0.0,
              "xba_allowed": 0.22,
              "xslg_allowed": 0.335,
              "xwoba_allowed": 0.192,
              "pitch_mix": {
                "FF": 52.2,
                "SI": 17.1,
                "ST": 14.3,
                "SL": 9.9,
                "CH": 6.5
              }
            }
          },
          "projection": {
            "ip_proj": 6.0,
            "outs_proj": 18.0,
            "k_proj": 5.8,
            "bb_proj": 1.0,
            "hits_proj": 3.7,
            "era_proj": 2.96,
            "runs_proj": 2.0,
            "er_proj": 2.0,
            "k_pct_adj": 27.6,
            "csw_pct": 29.4,
            "xfip": 2.9,
            "quality_start_prob": 77.0
          },
          "prop_lines": {
            "pitcher_strikeouts_over": {
              "fanduel": {
                "line": 5.5,
                "price": -166
              },
              "bovada": {
                "line": 5.5,
                "price": -165
              }
            },
            "pitcher_strikeouts_under": {
              "fanduel": {
                "line": 5.5,
                "price": 124
              },
              "bovada": {
                "line": 5.5,
                "price": 125
              }
            }
          },
          "edges": {}
        },
        "home": {
          "id": 669022,
          "name": "MacKenzie Gore",
          "hand": "L",
          "stats": {
            "id": 669022,
            "name": "MacKenzie Gore",
            "season": {
              "era": 4.2,
              "whip": 1.4,
              "ip": 159.7,
              "gs": 30,
              "k_pct": 27.2,
              "bb_pct": 9.4,
              "xera": null,
              "xfip": null,
              "swstr": null,
              "fip": null,
              "k_bb": null,
              "_source": "2025_only",
              "_blend": "prior_season_only"
            },
            "recent_form": {
              "total_pitches": 305,
              "ip_est": 4.7,
              "k_pct": 28.2,
              "bb_pct": 7.7,
              "swstr_pct": 12.5,
              "csw_pct": 26.9,
              "hard_hit_pct": 24.7,
              "barrel_pct": 1.0,
              "xba_allowed": 0.324,
              "xslg_allowed": 0.554,
              "xwoba_allowed": 0.273,
              "pitch_mix": {
                "FF": 43.0,
                "CU": 23.0,
                "CH": 13.4,
                "FC": 8.5,
                "SL": 7.5,
                "SI": 4.6
              }
            }
          },
          "projection": {
            "ip_proj": 5.1,
            "outs_proj": 15.3,
            "k_proj": 4.6,
            "bb_proj": 1.6,
            "hits_proj": 4.6,
            "era_proj": 4.26,
            "runs_proj": 2.4,
            "er_proj": 2.4,
            "k_pct_adj": 27.6,
            "csw_pct": 26.9,
            "xfip": 4.2,
            "quality_start_prob": 62.0
          },
          "prop_lines": {
            "pitcher_strikeouts_over": {
              "fanduel": {
                "line": 6.5,
                "price": 116
              },
              "bovada": {
                "line": 6.5,
                "price": 120
              }
            },
            "pitcher_strikeouts_under": {
              "fanduel": {
                "line": 6.5,
                "price": -158
              },
              "bovada": {
                "line": 6.5,
                "price": -160
              }
            }
          },
          "edges": {
            "K_under": {
              "proj": 4.6,
              "line": 6.5,
              "diff": -1.9,
              "edge_pct": -29.2,
              "lean": "UNDER",
              "flag": true,
              "best_book": "fanduel"
            }
          }
        }
      },
      "projected_boxscore": {
        "away": [],
        "home": []
      },
      "top_edges": [
        {
          "player": "MacKenzie Gore",
          "type": "K_under",
          "proj": 4.6,
          "line": 6.5,
          "diff": -1.9,
          "edge_pct": -29.2,
          "lean": "UNDER",
          "flag": true,
          "best_book": "fanduel"
        }
      ],
      "game_score": {},
      "game_line_edges": {}
    },
    {
      "game_pk": 822833,
      "game_date": "2026-04-08",
      "game_time": "2026-04-08T19:07:00Z",
      "status": "Preview",
      "venue": "Rogers Centre",
      "park_factors": {
        "hr": 100,
        "run": 100
      },
      "weather": {
        "condition": "",
        "temp_f": "",
        "wind": ""
      },
      "away": {
        "team_name": "Los Angeles Dodgers",
        "team_abbr": "LAD"
      },
      "home": {
        "team_name": "Toronto Blue Jays",
        "team_abbr": "TOR"
      },
      "pitchers": {
        "away": {
          "id": 660271,
          "name": "Shohei Ohtani",
          "hand": "R",
          "stats": {
            "id": 660271,
            "name": "Shohei Ohtani",
            "season": {
              "era": 2.9,
              "whip": 1.0,
              "ip": 47.0,
              "gs": 14,
              "k_pct": 33.0,
              "bb_pct": 4.8,
              "xera": null,
              "xfip": null,
              "swstr": null,
              "fip": null,
              "k_bb": null,
              "_source": "2025_only",
              "_blend": "prior_season_only"
            },
            "recent_form": {
              "total_pitches": 234,
              "ip_est": 4.7,
              "k_pct": 36.8,
              "bb_pct": 12.3,
              "swstr_pct": 15.0,
              "csw_pct": 32.9,
              "hard_hit_pct": 13.8,
              "barrel_pct": 0.0,
              "xba_allowed": 0.251,
              "xslg_allowed": 0.441,
              "xwoba_allowed": 0.291,
              "pitch_mix": {
                "FF": 35.0,
                "CU": 19.2,
                "ST": 16.2,
                "FS": 15.8,
                "SI": 12.0,
                "SL": 1.7
              }
            }
          },
          "projection": {
            "ip_proj": 3.9,
            "outs_proj": 11.7,
            "k_proj": 5.3,
            "bb_proj": 0.6,
            "hits_proj": 2.7,
            "era_proj": 2.9,
            "runs_proj": 1.3,
            "er_proj": 1.3,
            "k_pct_adj": 34.5,
            "csw_pct": 32.9,
            "xfip": 2.9,
            "quality_start_prob": 65.0
          },
          "prop_lines": {
            "batter_stolen_bases_over": {
              "fanduel": {
                "line": 0.5,
                "price": 240
              }
            },
            "pitcher_strikeouts_over": {
              "fanduel": {
                "line": 5.5,
                "price": -144
              },
              "bovada": {
                "line": 5.5,
                "price": -145
              }
            },
            "pitcher_strikeouts_under": {
              "fanduel": {
                "line": 5.5,
                "price": 108
              },
              "bovada": {
                "line": 5.5,
                "price": 110
              }
            }
          },
          "edges": {}
        },
        "home": {
          "id": 656302,
          "name": "Dylan Cease",
          "hand": "R",
          "stats": {
            "id": 656302,
            "name": "Dylan Cease",
            "season": {
              "era": 4.5,
              "whip": 1.3,
              "ip": 168.0,
              "gs": 32,
              "k_pct": 29.8,
              "bb_pct": 9.8,
              "xera": null,
              "xfip": null,
              "swstr": null,
              "fip": null,
              "k_bb": null,
              "_source": "2025_only",
              "_blend": "prior_season_only"
            },
            "recent_form": {
              "total_pitches": 320,
              "ip_est": 4.4,
              "k_pct": 35.5,
              "bb_pct": 9.2,
              "swstr_pct": 18.1,
              "csw_pct": 28.4,
              "hard_hit_pct": 16.5,
              "barrel_pct": 0.0,
              "xba_allowed": 0.396,
              "xslg_allowed": 0.502,
              "xwoba_allowed": 0.263,
              "pitch_mix": {
                "SL": 34.4,
                "FF": 29.4,
                "SI": 10.3,
                "KC": 10.0,
                "CH": 8.1,
                "ST": 7.8
              }
            }
          },
          "projection": {
            "ip_proj": 4.9,
            "outs_proj": 14.7,
            "k_proj": 5.4,
            "bb_proj": 1.6,
            "hits_proj": 5.4,
            "era_proj": 4.5,
            "runs_proj": 2.5,
            "er_proj": 2.5,
            "k_pct_adj": 32.1,
            "csw_pct": 28.4,
            "xfip": 4.5,
            "quality_start_prob": 58.0
          },
          "prop_lines": {
            "pitcher_strikeouts_over": {
              "fanduel": {
                "line": 6.5,
                "price": -166
              },
              "bovada": {
                "line": 6.5,
                "price": -165
              }
            },
            "pitcher_strikeouts_under": {
              "fanduel": {
                "line": 6.5,
                "price": 124
              },
              "bovada": {
                "line": 6.5,
                "price": 125
              }
            }
          },
          "edges": {
            "K_under": {
              "proj": 5.4,
              "line": 6.5,
              "diff": -1.1,
              "edge_pct": -16.9,
              "lean": "UNDER",
              "flag": true,
              "best_book": "fanduel"
            }
          }
        }
      },
      "projected_boxscore": {
        "away": [],
        "home": []
      },
      "top_edges": [
        {
          "player": "Dylan Cease",
          "type": "K_under",
          "proj": 5.4,
          "line": 6.5,
          "diff": -1.1,
          "edge_pct": -16.9,
          "lean": "UNDER",
          "flag": true,
          "best_book": "fanduel"
        }
      ],
      "game_score": {},
      "game_line_edges": {}
    },
    {
      "game_pk": 824374,
      "game_date": "2026-04-08",
      "game_time": "2026-04-08T19:10:00Z",
      "status": "Preview",
      "venue": "Coors Field",
      "park_factors": {
        "hr": 128,
        "run": 115
      },
      "weather": {
        "condition": "",
        "temp_f": "",
        "wind": ""
      },
      "away": {
        "team_name": "Houston Astros",
        "team_abbr": "HOU"
      },
      "home": {
        "team_name": "Colorado Rockies",
        "team_abbr": "COL"
      },
      "pitchers": {
        "away": {
          "id": 664299,
          "name": "Cristian Javier",
          "hand": "R",
          "stats": {
            "id": 664299,
            "name": "Cristian Javier",
            "season": {
              "era": 4.6,
              "whip": 1.3,
              "ip": 37.0,
              "gs": 8,
              "k_pct": 21.7,
              "bb_pct": 9.6,
              "xera": null,
              "xfip": null,
              "swstr": null,
              "fip": null,
              "k_bb": null,
              "_source": "2025_only",
              "_blend": "prior_season_only"
            },
            "recent_form": {
              "total_pitches": 334,
              "ip_est": 3.5,
              "k_pct": 14.9,
              "bb_pct": 17.2,
              "swstr_pct": 12.0,
              "csw_pct": 24.9,
              "hard_hit_pct": 22.8,
              "barrel_pct": 0.0,
              "xba_allowed": 0.283,
              "xslg_allowed": 0.472,
              "xwoba_allowed": 0.401,
              "pitch_mix": {
                "FF": 46.2,
                "ST": 23.7,
                "CH": 18.9,
                "SI": 7.2,
                "KC": 3.9
              }
            }
          },
          "projection": {
            "ip_proj": 4.2,
            "outs_proj": 12.6,
            "k_proj": 2.6,
            "bb_proj": 1.3,
            "hits_proj": 3.3,
            "era_proj": 5.05,
            "runs_proj": 2.4,
            "er_proj": 2.4,
            "k_pct_adj": 19.0,
            "csw_pct": 24.9,
            "xfip": 4.6,
            "quality_start_prob": 50.0
          },
          "prop_lines": {},
          "edges": {}
        },
        "home": {
          "id": 547179,
          "name": "Michael Lorenzen",
          "hand": "R",
          "stats": {
            "id": 547179,
            "name": "Michael Lorenzen",
            "season": {
              "era": 4.6,
              "whip": 1.3,
              "ip": 141.7,
              "gs": 26,
              "k_pct": 21.0,
              "bb_pct": 6.4,
              "xera": null,
              "xfip": null,
              "swstr": null,
              "fip": null,
              "k_bb": null,
              "_source": "2025_only",
              "_blend": "prior_season_only"
            },
            "recent_form": {
              "total_pitches": 243,
              "ip_est": 3.9,
              "k_pct": 13.6,
              "bb_pct": 7.6,
              "swstr_pct": 9.5,
              "csw_pct": 25.1,
              "hard_hit_pct": 39.0,
              "barrel_pct": 3.7,
              "xba_allowed": 0.459,
              "xslg_allowed": 0.735,
              "xwoba_allowed": 0.457,
              "pitch_mix": {
                "FF": 19.8,
                "CH": 18.5,
                "SI": 17.7,
                "SL": 13.2,
                "CU": 12.8,
                "FC": 9.1,
                "ST": 9.1
              }
            }
          },
          "projection": {
            "ip_proj": 4.8,
            "outs_proj": 14.4,
            "k_proj": 2.9,
            "bb_proj": 1.0,
            "hits_proj": 6.2,
            "era_proj": 5.05,
            "runs_proj": 2.7,
            "er_proj": 2.7,
            "k_pct_adj": 18.0,
            "csw_pct": 25.1,
            "xfip": 4.6,
            "quality_start_prob": 53.0
          },
          "prop_lines": {},
          "edges": {}
        }
      },
      "projected_boxscore": {
        "away": [],
        "home": []
      },
      "top_edges": [],
      "game_score": {},
      "game_line_edges": {}
    },
    {
      "game_pk": 823234,
      "game_date": "2026-04-08",
      "game_time": "2026-04-08T19:45:00Z",
      "status": "Preview",
      "venue": "Oracle Park",
      "park_factors": {
        "hr": 82,
        "run": 88
      },
      "weather": {
        "condition": "",
        "temp_f": "",
        "wind": ""
      },
      "away": {
        "team_name": "Philadelphia Phillies",
        "team_abbr": "PHI"
      },
      "home": {
        "team_name": "San Francisco Giants",
        "team_abbr": "SF"
      },
      "pitchers": {
        "away": {
          "id": 605400,
          "name": "Aaron Nola",
          "hand": "R",
          "stats": {
            "id": 605400,
            "name": "Aaron Nola",
            "season": {
              "era": 6.0,
              "whip": 1.4,
              "ip": 94.3,
              "gs": 17,
              "k_pct": 24.0,
              "bb_pct": 6.9,
              "xera": null,
              "xfip": null,
              "swstr": null,
              "fip": null,
              "k_bb": null,
              "_source": "2025_only",
              "_blend": "prior_season_only"
            },
            "recent_form": {
              "total_pitches": 265,
              "ip_est": 5.0,
              "k_pct": 29.9,
              "bb_pct": 9.0,
              "swstr_pct": 11.7,
              "csw_pct": 29.8,
              "hard_hit_pct": 25.3,
              "barrel_pct": 2.5,
              "xba_allowed": 0.382,
              "xslg_allowed": 0.699,
              "xwoba_allowed": 0.319,
              "pitch_mix": {
                "FF": 33.6,
                "KC": 28.3,
                "SI": 15.1,
                "CH": 13.2,
                "FC": 9.8
              }
            }
          },
          "projection": {
            "ip_proj": 5.3,
            "outs_proj": 15.9,
            "k_proj": 5.0,
            "bb_proj": 1.2,
            "hits_proj": 5.7,
            "era_proj": 5.64,
            "runs_proj": 3.3,
            "er_proj": 3.3,
            "k_pct_adj": 26.4,
            "csw_pct": 29.8,
            "xfip": 6.0,
            "quality_start_prob": 52.0
          },
          "prop_lines": {},
          "edges": {}
        },
        "home": {
          "id": 641816,
          "name": "Tyler Mahle",
          "hand": "R",
          "stats": {
            "id": 641816,
            "name": "Tyler Mahle",
            "season": {
              "era": 2.2,
              "whip": 1.1,
              "ip": 86.7,
              "gs": 16,
              "k_pct": 19.1,
              "bb_pct": 8.4,
              "xera": null,
              "xfip": null,
              "swstr": null,
              "fip": null,
              "k_bb": null,
              "_source": "2025_only",
              "_blend": "prior_season_only"
            },
            "recent_form": {
              "total_pitches": 272,
              "ip_est": 3.8,
              "k_pct": 23.9,
              "bb_pct": 9.0,
              "swstr_pct": 8.8,
              "csw_pct": 27.6,
              "hard_hit_pct": 25.6,
              "barrel_pct": 2.3,
              "xba_allowed": 0.439,
              "xslg_allowed": 0.799,
              "xwoba_allowed": 0.423,
              "pitch_mix": {
                "FF": 48.5,
                "FS": 32.7,
                "SL": 11.0,
                "FC": 7.7
              }
            }
          },
          "projection": {
            "ip_proj": 4.8,
            "outs_proj": 14.4,
            "k_proj": 3.4,
            "bb_proj": 1.3,
            "hits_proj": 5.9,
            "era_proj": 1.84,
            "runs_proj": 1.0,
            "er_proj": 1.0,
            "k_pct_adj": 21.0,
            "csw_pct": 27.6,
            "xfip": 2.2,
            "quality_start_prob": 79.0
          },
          "prop_lines": {},
          "edges": {}
        }
      },
      "projected_boxscore": {
        "away": [],
        "home": []
      },
      "top_edges": [],
      "game_score": {},
      "game_line_edges": {}
    },
    {
      "game_pk": 822753,
      "game_date": "2026-04-08",
      "game_time": "2026-04-08T20:05:00Z",
      "status": "Preview",
      "venue": "Nationals Park",
      "park_factors": {
        "hr": 100,
        "run": 100
      },
      "weather": {
        "condition": "",
        "temp_f": "",
        "wind": ""
      },
      "away": {
        "team_name": "St. Louis Cardinals",
        "team_abbr": "STL"
      },
      "home": {
        "team_name": "Washington Nationals",
        "team_abbr": "WSH"
      },
      "pitchers": {
        "away": {
          "id": 700241,
          "name": "Michael McGreevy",
          "hand": "R",
          "stats": {
            "id": 700241,
            "name": "Michael McGreevy",
            "season": {
              "era": 4.4,
              "whip": 1.2,
              "ip": 95.7,
              "gs": 16,
              "k_pct": 14.5,
              "bb_pct": 5.0,
              "xera": null,
              "xfip": null,
              "swstr": null,
              "fip": null,
              "k_bb": null,
              "_source": "2025_only",
              "_blend": "prior_season_only"
            },
            "recent_form": {
              "total_pitches": 305,
              "ip_est": 5.0,
              "k_pct": 21.8,
              "bb_pct": 3.8,
              "swstr_pct": 6.9,
              "csw_pct": 26.6,
              "hard_hit_pct": 19.4,
              "barrel_pct": 4.3,
              "xba_allowed": 0.357,
              "xslg_allowed": 0.906,
              "xwoba_allowed": 0.421,
              "pitch_mix": {
                "FF": 22.6,
                "CH": 19.7,
                "SI": 18.4,
                "FC": 11.1,
                "ST": 10.8,
                "CU": 9.5,
                "SL": 7.9
              }
            }
          },
          "projection": {
            "ip_proj": 5.6,
            "outs_proj": 16.8,
            "k_proj": 3.2,
            "bb_proj": 0.9,
            "hits_proj": 5.6,
            "era_proj": 4.4,
            "runs_proj": 2.7,
            "er_proj": 2.7,
            "k_pct_adj": 17.4,
            "csw_pct": 26.6,
            "xfip": 4.4,
            "quality_start_prob": 63.0
          },
          "prop_lines": {},
          "edges": {}
        },
        "home": {
          "id": 571945,
          "name": "Miles Mikolas",
          "hand": "R",
          "stats": {
            "id": 571945,
            "name": "Miles Mikolas",
            "season": {
              "era": 4.8,
              "whip": 1.3,
              "ip": 156.3,
              "gs": 31,
              "k_pct": 14.9,
              "bb_pct": 5.5,
              "xera": null,
              "xfip": null,
              "swstr": null,
              "fip": null,
              "k_bb": null,
              "_source": "2025_only",
              "_blend": "prior_season_only"
            },
            "recent_form": {
              "total_pitches": 267,
              "ip_est": 4.6,
              "k_pct": 12.5,
              "bb_pct": 9.7,
              "swstr_pct": 7.9,
              "csw_pct": 22.5,
              "hard_hit_pct": 33.7,
              "barrel_pct": 4.3,
              "xba_allowed": 0.353,
              "xslg_allowed": 0.823,
              "xwoba_allowed": 0.422,
              "pitch_mix": {
                "SL": 21.0,
                "FF": 20.6,
                "SI": 18.0,
                "CU": 16.5,
                "CH": 15.7,
                "ST": 8.2
              }
            }
          },
          "projection": {
            "ip_proj": 4.9,
            "outs_proj": 14.7,
            "k_proj": 2.2,
            "bb_proj": 0.9,
            "hits_proj": 4.9,
            "era_proj": 4.8,
            "runs_proj": 2.6,
            "er_proj": 2.6,
            "k_pct_adj": 13.9,
            "csw_pct": 22.5,
            "xfip": 4.8,
            "quality_start_prob": 56.0
          },
          "prop_lines": {},
          "edges": {}
        }
      },
      "projected_boxscore": {
        "away": [],
        "home": []
      },
      "top_edges": [],
      "game_score": {},
      "game_line_edges": {}
    },
    {
      "game_pk": 824050,
      "game_date": "2026-04-08",
      "game_time": "2026-04-08T20:07:00Z",
      "status": "Preview",
      "venue": "Angel Stadium",
      "park_factors": {
        "hr": 100,
        "run": 100
      },
      "weather": {
        "condition": "",
        "temp_f": "",
        "wind": ""
      },
      "away": {
        "team_name": "Atlanta Braves",
        "team_abbr": "ATL"
      },
      "home": {
        "team_name": "Los Angeles Angels",
        "team_abbr": "LAA"
      },
      "pitchers": {
        "away": {
          "id": 656550,
          "name": "Grant Holmes",
          "hand": "R",
          "stats": {
            "id": 656550,
            "name": "Grant Holmes",
            "season": {
              "era": 4.0,
              "whip": 1.3,
              "ip": 115.0,
              "gs": 21,
              "k_pct": 25.0,
              "bb_pct": 11.0,
              "xera": null,
              "xfip": null,
              "swstr": null,
              "fip": null,
              "k_bb": null,
              "_source": "2025_only",
              "_blend": "prior_season_only"
            },
            "recent_form": {
              "total_pitches": 303,
              "ip_est": 5.1,
              "k_pct": 26.2,
              "bb_pct": 11.2,
              "swstr_pct": 15.2,
              "csw_pct": 30.0,
              "hard_hit_pct": 30.5,
              "barrel_pct": 2.4,
              "xba_allowed": 0.247,
              "xslg_allowed": 0.398,
              "xwoba_allowed": 0.274,
              "pitch_mix": {
                "SL": 38.9,
                "FF": 31.0,
                "CU": 12.5,
                "FC": 6.6,
                "SI": 5.9,
                "CH": 5.0
              }
            }
          },
          "projection": {
            "ip_proj": 5.3,
            "outs_proj": 15.9,
            "k_proj": 4.9,
            "bb_proj": 1.9,
            "hits_proj": 3.7,
            "era_proj": 4.0,
            "runs_proj": 2.4,
            "er_proj": 2.4,
            "k_pct_adj": 25.5,
            "csw_pct": 30.0,
            "xfip": 4.0,
            "quality_start_prob": 65.0
          },
          "prop_lines": {},
          "edges": {}
        },
        "home": {
          "id": 672282,
          "name": "Reid Detmers",
          "hand": "L",
          "stats": {
            "id": 672282,
            "name": "Reid Detmers",
            "season": {
              "era": 4.0,
              "whip": 1.3,
              "ip": 63.7,
              "gs": 0,
              "k_pct": 30.1,
              "bb_pct": 9.4,
              "xera": null,
              "xfip": null,
              "swstr": null,
              "fip": null,
              "k_bb": null,
              "_source": "2025_only",
              "_blend": "prior_season_only"
            },
            "recent_form": {
              "total_pitches": 266,
              "ip_est": 4.7,
              "k_pct": 26.2,
              "bb_pct": 11.5,
              "swstr_pct": 12.0,
              "csw_pct": 29.3,
              "hard_hit_pct": 20.7,
              "barrel_pct": 0.0,
              "xba_allowed": 0.278,
              "xslg_allowed": 0.366,
              "xwoba_allowed": 0.247,
              "pitch_mix": {
                "FF": 43.0,
                "SL": 34.0,
                "CU": 9.8,
                "CH": 9.1,
                "SI": 4.2
              }
            }
          },
          "projection": {
            "ip_proj": 4.7,
            "outs_proj": 14.1,
            "k_proj": 4.8,
            "bb_proj": 1.5,
            "hits_proj": 3.7,
            "era_proj": 4.0,
            "runs_proj": 2.1,
            "er_proj": 2.1,
            "k_pct_adj": 28.5,
            "csw_pct": 29.3,
            "xfip": 4.0,
            "quality_start_prob": 61.0
          },
          "prop_lines": {},
          "edges": {}
        }
      },
      "projected_boxscore": {
        "away": [],
        "home": []
      },
      "top_edges": [],
      "game_score": {},
      "game_line_edges": {}
    },
    {
      "game_pk": 823646,
      "game_date": "2026-04-08",
      "game_time": "2026-04-08T20:10:00Z",
      "status": "Preview",
      "venue": "Citi Field",
      "park_factors": {
        "hr": 100,
        "run": 100
      },
      "weather": {
        "condition": "",
        "temp_f": "",
        "wind": ""
      },
      "away": {
        "team_name": "Arizona Diamondbacks",
        "team_abbr": "AZ"
      },
      "home": {
        "team_name": "New York Mets",
        "team_abbr": "NYM"
      },
      "pitchers": {
        "away": {
          "id": 669194,
          "name": "Ryne Nelson",
          "hand": "R",
          "stats": {
            "id": 669194,
            "name": "Ryne Nelson",
            "season": {
              "era": 3.4,
              "whip": 1.1,
              "ip": 154.0,
              "gs": 23,
              "k_pct": 21.3,
              "bb_pct": 6.6,
              "xera": null,
              "xfip": null,
              "swstr": null,
              "fip": null,
              "k_bb": null,
              "_source": "2025_only",
              "_blend": "prior_season_only"
            },
            "recent_form": {
              "total_pitches": 356,
              "ip_est": 4.2,
              "k_pct": 27.3,
              "bb_pct": 9.1,
              "swstr_pct": 12.4,
              "csw_pct": 26.1,
              "hard_hit_pct": 31.3,
              "barrel_pct": 4.3,
              "xba_allowed": 0.388,
              "xslg_allowed": 0.938,
              "xwoba_allowed": 0.48,
              "pitch_mix": {
                "FF": 60.4,
                "SL": 19.7,
                "CU": 14.3,
                "FC": 5.6
              }
            }
          },
          "projection": {
            "ip_proj": 5.7,
            "outs_proj": 17.1,
            "k_proj": 4.5,
            "bb_proj": 1.2,
            "hits_proj": 6.2,
            "era_proj": 3.4,
            "runs_proj": 2.2,
            "er_proj": 2.2,
            "k_pct_adj": 23.7,
            "csw_pct": 26.1,
            "xfip": 3.4,
            "quality_start_prob": 72.0
          },
          "prop_lines": {},
          "edges": {}
        },
        "home": {
          "id": 656849,
          "name": "David Peterson",
          "hand": "L",
          "stats": {
            "id": 656849,
            "name": "David Peterson",
            "season": {
              "era": 4.2,
              "whip": 1.4,
              "ip": 168.7,
              "gs": 30,
              "k_pct": 20.7,
              "bb_pct": 9.0,
              "xera": null,
              "xfip": null,
              "swstr": null,
              "fip": null,
              "k_bb": null,
              "_source": "2025_only",
              "_blend": "prior_season_only"
            },
            "recent_form": {
              "total_pitches": 341,
              "ip_est": 4.3,
              "k_pct": 16.5,
              "bb_pct": 6.8,
              "swstr_pct": 11.7,
              "csw_pct": 27.9,
              "hard_hit_pct": 31.0,
              "barrel_pct": 0.0,
              "xba_allowed": 0.342,
              "xslg_allowed": 0.425,
              "xwoba_allowed": 0.328,
              "pitch_mix": {
                "SI": 30.5,
                "FF": 22.9,
                "SL": 18.5,
                "CH": 17.0,
                "CU": 11.1
              }
            }
          },
          "projection": {
            "ip_proj": 5.1,
            "outs_proj": 15.3,
            "k_proj": 3.3,
            "bb_proj": 1.5,
            "hits_proj": 4.9,
            "era_proj": 4.2,
            "runs_proj": 2.4,
            "er_proj": 2.4,
            "k_pct_adj": 19.0,
            "csw_pct": 27.9,
            "xfip": 4.2,
            "quality_start_prob": 62.0
          },
          "prop_lines": {},
          "edges": {}
        }
      },
      "projected_boxscore": {
        "away": [],
        "home": []
      },
      "top_edges": [],
      "game_score": {},
      "game_line_edges": {}
    },
    {
      "game_pk": 823000,
      "game_date": "2026-04-08",
      "game_time": "2026-04-08T22:40:00Z",
      "status": "Preview",
      "venue": "Tropicana Field",
      "park_factors": {
        "hr": 100,
        "run": 100
      },
      "weather": {
        "condition": "",
        "temp_f": "",
        "wind": ""
      },
      "away": {
        "team_name": "Chicago Cubs",
        "team_abbr": "CHC"
      },
      "home": {
        "team_name": "Tampa Bay Rays",
        "team_abbr": "TB"
      },
      "pitchers": {
        "away": {
          "id": 607067,
          "name": "Colin Rea",
          "hand": "R",
          "stats": {
            "id": 607067,
            "name": "Colin Rea",
            "season": {
              "era": 4.0,
              "whip": 1.2,
              "ip": 159.3,
              "gs": 27,
              "k_pct": 19.2,
              "bb_pct": 6.6,
              "xera": null,
              "xfip": null,
              "swstr": null,
              "fip": null,
              "k_bb": null,
              "_source": "2025_only",
              "_blend": "prior_season_only"
            },
            "recent_form": {
              "total_pitches": 293,
              "ip_est": 3.5,
              "k_pct": 21.5,
              "bb_pct": 7.6,
              "swstr_pct": 11.6,
              "csw_pct": 26.3,
              "hard_hit_pct": 28.1,
              "barrel_pct": 1.0,
              "xba_allowed": 0.433,
              "xslg_allowed": 0.747,
              "xwoba_allowed": 0.356,
              "pitch_mix": {
                "FF": 38.9,
                "SL": 14.3,
                "FS": 12.3,
                "SI": 9.9,
                "FC": 9.9,
                "CU": 9.2,
                "ST": 5.5
              }
            }
          },
          "projection": {
            "ip_proj": 4.9,
            "outs_proj": 14.7,
            "k_proj": 3.3,
            "bb_proj": 1.1,
            "hits_proj": 6.0,
            "era_proj": 4.0,
            "runs_proj": 2.2,
            "er_proj": 2.2,
            "k_pct_adj": 20.1,
            "csw_pct": 26.3,
            "xfip": 4.0,
            "quality_start_prob": 62.0
          },
          "prop_lines": {},
          "edges": {}
        },
        "home": {
          "id": 671212,
          "name": "Joe Boyle",
          "hand": "R",
          "stats": {
            "id": 671212,
            "name": "Joe Boyle",
            "season": {
              "era": 4.7,
              "whip": 1.4,
              "ip": 52.0,
              "gs": 9,
              "k_pct": 25.7,
              "bb_pct": 12.4,
              "xera": null,
              "xfip": null,
              "swstr": null,
              "fip": null,
              "k_bb": null,
              "_source": "2025_only",
              "_blend": "prior_season_only"
            },
            "recent_form": {
              "total_pitches": 253,
              "ip_est": 4.8,
              "k_pct": 31.1,
              "bb_pct": 11.5,
              "swstr_pct": 12.6,
              "csw_pct": 30.8,
              "hard_hit_pct": 24.0,
              "barrel_pct": 4.0,
              "xba_allowed": 0.355,
              "xslg_allowed": 0.517,
              "xwoba_allowed": 0.288,
              "pitch_mix": {
                "SL": 35.2,
                "FF": 24.9,
                "FS": 17.4,
                "SI": 11.5,
                "ST": 11.1
              }
            }
          },
          "projection": {
            "ip_proj": 5.4,
            "outs_proj": 16.2,
            "k_proj": 5.5,
            "bb_proj": 2.2,
            "hits_proj": 5.4,
            "era_proj": 4.7,
            "runs_proj": 2.8,
            "er_proj": 2.8,
            "k_pct_adj": 27.9,
            "csw_pct": 30.8,
            "xfip": 4.7,
            "quality_start_prob": 60.0
          },
          "prop_lines": {},
          "edges": {}
        }
      },
      "projected_boxscore": {
        "away": [],
        "home": []
      },
      "top_edges": [],
      "game_score": {},
      "game_line_edges": {}
    },
    {
      "game_pk": 823885,
      "game_date": "2026-04-08",
      "game_time": "2026-04-08T22:40:00Z",
      "status": "Preview",
      "venue": "loanDepot park",
      "park_factors": {
        "hr": 100,
        "run": 100
      },
      "weather": {
        "condition": "",
        "temp_f": "",
        "wind": ""
      },
      "away": {
        "team_name": "Cincinnati Reds",
        "team_abbr": "CIN"
      },
      "home": {
        "team_name": "Miami Marlins",
        "team_abbr": "MIA"
      },
      "pitchers": {
        "away": {
          "id": 663903,
          "name": "Brady Singer",
          "hand": "R",
          "stats": {
            "id": 663903,
            "name": "Brady Singer",
            "season": {
              "era": 4.0,
              "whip": 1.2,
              "ip": 169.7,
              "gs": 32,
              "k_pct": 22.8,
              "bb_pct": 8.4,
              "xera": null,
              "xfip": null,
              "swstr": null,
              "fip": null,
              "k_bb": null,
              "_source": "2025_only",
              "_blend": "prior_season_only"
            },
            "recent_form": {
              "total_pitches": 349,
              "ip_est": 4.0,
              "k_pct": 20.0,
              "bb_pct": 7.8,
              "swstr_pct": 9.5,
              "csw_pct": 28.7,
              "hard_hit_pct": 33.6,
              "barrel_pct": 0.9,
              "xba_allowed": 0.453,
              "xslg_allowed": 0.663,
              "xwoba_allowed": 0.385,
              "pitch_mix": {
                "SI": 53.0,
                "SL": 30.4,
                "ST": 7.7,
                "FC": 5.7,
                "FF": 3.2
              }
            }
          },
          "projection": {
            "ip_proj": 4.8,
            "outs_proj": 14.4,
            "k_proj": 3.7,
            "bb_proj": 1.3,
            "hits_proj": 6.1,
            "era_proj": 4.0,
            "runs_proj": 2.1,
            "er_proj": 2.1,
            "k_pct_adj": 21.7,
            "csw_pct": 28.7,
            "xfip": 4.0,
            "quality_start_prob": 62.0
          },
          "prop_lines": {},
          "edges": {}
        },
        "home": {
          "id": 691587,
          "name": "Eury P\u00e9rez",
          "hand": "R",
          "stats": {
            "id": 691587,
            "name": "Eury P\u00e9rez",
            "season": {
              "era": 4.2,
              "whip": 1.1,
              "ip": 95.3,
              "gs": 20,
              "k_pct": 27.3,
              "bb_pct": 8.3,
              "xera": null,
              "xfip": null,
              "swstr": null,
              "fip": null,
              "k_bb": null,
              "_source": "2025_only",
              "_blend": "prior_season_only"
            },
            "recent_form": {
              "total_pitches": 367,
              "ip_est": 4.5,
              "k_pct": 31.5,
              "bb_pct": 12.0,
              "swstr_pct": 16.6,
              "csw_pct": 29.2,
              "hard_hit_pct": 29.7,
              "barrel_pct": 2.0,
              "xba_allowed": 0.317,
              "xslg_allowed": 0.706,
              "xwoba_allowed": 0.369,
              "pitch_mix": {
                "FF": 45.6,
                "SL": 16.9,
                "CH": 14.2,
                "ST": 11.5,
                "CU": 9.6,
                "FC": 2.2
              }
            }
          },
          "projection": {
            "ip_proj": 4.7,
            "outs_proj": 14.1,
            "k_proj": 4.8,
            "bb_proj": 1.3,
            "hits_proj": 4.2,
            "era_proj": 4.2,
            "runs_proj": 2.2,
            "er_proj": 2.2,
            "k_pct_adj": 29.0,
            "csw_pct": 29.2,
            "xfip": 4.2,
            "quality_start_prob": 60.0
          },
          "prop_lines": {},
          "edges": {}
        }
      },
      "projected_boxscore": {
        "away": [],
        "home": []
      },
      "top_edges": [],
      "game_score": {},
      "game_line_edges": {}
    },
    {
      "game_pk": 823564,
      "game_date": "2026-04-08",
      "game_time": "2026-04-08T23:05:00Z",
      "status": "Preview",
      "venue": "Yankee Stadium",
      "park_factors": {
        "hr": 100,
        "run": 100
      },
      "weather": {
        "condition": "",
        "temp_f": "",
        "wind": ""
      },
      "away": {
        "team_name": "Athletics",
        "team_abbr": "ATH"
      },
      "home": {
        "team_name": "New York Yankees",
        "team_abbr": "NYY"
      },
      "pitchers": {
        "away": {
          "id": 622663,
          "name": "Luis Severino",
          "hand": "R",
          "stats": {
            "id": 622663,
            "name": "Luis Severino",
            "season": {
              "era": 4.5,
              "whip": 1.3,
              "ip": 162.7,
              "gs": 29,
              "k_pct": 17.6,
              "bb_pct": 7.1,
              "xera": null,
              "xfip": null,
              "swstr": null,
              "fip": null,
              "k_bb": null,
              "_source": "2025_only",
              "_blend": "prior_season_only"
            },
            "recent_form": {
              "total_pitches": 254,
              "ip_est": 4.2,
              "k_pct": 29.8,
              "bb_pct": 17.5,
              "swstr_pct": 9.4,
              "csw_pct": 24.0,
              "hard_hit_pct": 24.0,
              "barrel_pct": 2.7,
              "xba_allowed": 0.331,
              "xslg_allowed": 0.502,
              "xwoba_allowed": 0.336,
              "pitch_mix": {
                "SI": 25.6,
                "FC": 25.2,
                "FF": 19.3,
                "ST": 18.1,
                "CH": 9.1,
                "SL": 2.8
              }
            }
          },
          "projection": {
            "ip_proj": 5.0,
            "outs_proj": 15.0,
            "k_proj": 3.7,
            "bb_proj": 1.2,
            "hits_proj": 4.6,
            "era_proj": 4.5,
            "runs_proj": 2.5,
            "er_proj": 2.5,
            "k_pct_adj": 22.5,
            "csw_pct": 24.0,
            "xfip": 4.5,
            "quality_start_prob": 59.0
          },
          "prop_lines": {},
          "edges": {}
        },
        "home": {
          "id": 701542,
          "name": "Will Warren",
          "hand": "R",
          "stats": {
            "id": 701542,
            "name": "Will Warren",
            "season": {
              "era": 4.4,
              "whip": 1.4,
              "ip": 162.3,
              "gs": 33,
              "k_pct": 24.1,
              "bb_pct": 9.1,
              "xera": null,
              "xfip": null,
              "swstr": null,
              "fip": null,
              "k_bb": null,
              "_source": "2025_only",
              "_blend": "prior_season_only"
            },
            "recent_form": {
              "total_pitches": 354,
              "ip_est": 4.9,
              "k_pct": 22.8,
              "bb_pct": 3.3,
              "swstr_pct": 12.1,
              "csw_pct": 30.8,
              "hard_hit_pct": 30.2,
              "barrel_pct": 0.0,
              "xba_allowed": 0.286,
              "xslg_allowed": 0.47,
              "xwoba_allowed": 0.271,
              "pitch_mix": {
                "FF": 48.3,
                "SI": 22.6,
                "ST": 19.8,
                "CU": 5.9,
                "CH": 3.4
              }
            }
          },
          "projection": {
            "ip_proj": 4.9,
            "outs_proj": 14.7,
            "k_proj": 4.4,
            "bb_proj": 1.5,
            "hits_proj": 3.9,
            "era_proj": 4.4,
            "runs_proj": 2.4,
            "er_proj": 2.4,
            "k_pct_adj": 23.6,
            "csw_pct": 30.8,
            "xfip": 4.4,
            "quality_start_prob": 59.0
          },
          "prop_lines": {},
          "edges": {}
        }
      },
      "projected_boxscore": {
        "away": [],
        "home": []
      },
      "top_edges": [],
      "game_score": {},
      "game_line_edges": {}
    },
    {
      "game_pk": 823726,
      "game_date": "2026-04-08",
      "game_time": "2026-04-08T23:40:00Z",
      "status": "Preview",
      "venue": "Target Field",
      "park_factors": {
        "hr": 100,
        "run": 100
      },
      "weather": {
        "condition": "",
        "temp_f": "",
        "wind": ""
      },
      "away": {
        "team_name": "Detroit Tigers",
        "team_abbr": "DET"
      },
      "home": {
        "team_name": "Minnesota Twins",
        "team_abbr": "MIN"
      },
      "pitchers": {
        "away": {
          "id": 664285,
          "name": "Framber Valdez",
          "hand": "L",
          "stats": {
            "id": 664285,
            "name": "Framber Valdez",
            "season": {
              "era": 3.7,
              "whip": 1.2,
              "ip": 192.0,
              "gs": 31,
              "k_pct": 23.3,
              "bb_pct": 8.5,
              "xera": null,
              "xfip": null,
              "swstr": null,
              "fip": null,
              "k_bb": null,
              "_source": "2025_only",
              "_blend": "prior_season_only"
            },
            "recent_form": {
              "total_pitches": 367,
              "ip_est": 5.1,
              "k_pct": 21.5,
              "bb_pct": 4.7,
              "swstr_pct": 10.4,
              "csw_pct": 27.2,
              "hard_hit_pct": 31.6,
              "barrel_pct": 0.7,
              "xba_allowed": 0.273,
              "xslg_allowed": 0.381,
              "xwoba_allowed": 0.251,
              "pitch_mix": {
                "SI": 49.0,
                "CU": 27.8,
                "CH": 19.6,
                "SL": 3.3,
                "FF": 0.3
              }
            }
          },
          "projection": {
            "ip_proj": 5.8,
            "outs_proj": 17.4,
            "k_proj": 4.4,
            "bb_proj": 1.6,
            "hits_proj": 4.4,
            "era_proj": 3.7,
            "runs_proj": 2.4,
            "er_proj": 2.4,
            "k_pct_adj": 22.6,
            "csw_pct": 27.2,
            "xfip": 3.7,
            "quality_start_prob": 70.0
          },
          "prop_lines": {},
          "edges": {}
        },
        "home": {
          "id": 641927,
          "name": "Bailey Ober",
          "hand": "R",
          "stats": {
            "id": 641927,
            "name": "Bailey Ober",
            "season": {
              "era": 5.1,
              "whip": 1.3,
              "ip": 146.3,
              "gs": 27,
              "k_pct": 19.2,
              "bb_pct": 5.0,
              "xera": null,
              "xfip": null,
              "swstr": null,
              "fip": null,
              "k_bb": null,
              "_source": "2025_only",
              "_blend": "prior_season_only"
            },
            "recent_form": {
              "total_pitches": 330,
              "ip_est": 3.5,
              "k_pct": 11.4,
              "bb_pct": 10.2,
              "swstr_pct": 9.1,
              "csw_pct": 23.6,
              "hard_hit_pct": 26.7,
              "barrel_pct": 2.6,
              "xba_allowed": 0.343,
              "xslg_allowed": 0.525,
              "xwoba_allowed": 0.348,
              "pitch_mix": {
                "CH": 36.7,
                "FF": 28.8,
                "SL": 16.4,
                "ST": 7.9,
                "SI": 6.7,
                "CU": 3.6
              }
            }
          },
          "projection": {
            "ip_proj": 4.7,
            "outs_proj": 14.1,
            "k_proj": 2.5,
            "bb_proj": 0.8,
            "hits_proj": 4.5,
            "era_proj": 5.1,
            "runs_proj": 2.7,
            "er_proj": 2.7,
            "k_pct_adj": 16.1,
            "csw_pct": 23.6,
            "xfip": 5.1,
            "quality_start_prob": 52.0
          },
          "prop_lines": {},
          "edges": {}
        }
      },
      "projected_boxscore": {
        "away": [],
        "home": []
      },
      "top_edges": [],
      "game_score": {},
      "game_line_edges": {}
    }
  ]
}